neural_coder/__init__.py
neural_coder/__main__.py
neural_coder/globals.py
neural_coder/interface.py
neural_coder/launcher.py
neural_coder/version.py
neural_coder/backends/__init__.py
neural_coder/backends/intel_extension_for_transformers.yaml
neural_coder/backends/keras_inc.yaml
neural_coder/backends/nano_bf16.yaml
neural_coder/backends/nano_bf16_channels_last.yaml
neural_coder/backends/nano_bf16_ipex.yaml
neural_coder/backends/nano_bf16_ipex_channels_last.yaml
neural_coder/backends/nano_fp32_channels_last.yaml
neural_coder/backends/nano_fp32_ipex.yaml
neural_coder/backends/nano_fp32_ipex_channels_last.yaml
neural_coder/backends/nano_gpu_to_cpu.yaml
neural_coder/backends/nano_int8.yaml
neural_coder/backends/nano_jit_bf16.yaml
neural_coder/backends/nano_jit_bf16_channels_last.yaml
neural_coder/backends/nano_jit_bf16_ipex.yaml
neural_coder/backends/nano_jit_bf16_ipex_channels_last.yaml
neural_coder/backends/nano_jit_fp32.yaml
neural_coder/backends/nano_jit_fp32_channels_last.yaml
neural_coder/backends/nano_jit_fp32_ipex.yaml
neural_coder/backends/nano_jit_fp32_ipex_channels_last.yaml
neural_coder/backends/nano_onnxruntime_fp32.yaml
neural_coder/backends/nano_onnxruntime_int8_qlinear.yaml
neural_coder/backends/nano_openvino_fp32.yaml
neural_coder/backends/nano_openvino_int8.yaml
neural_coder/backends/onnx_inc_dynamic_quant.yaml
neural_coder/backends/onnx_inc_static_quant_qdq.yaml
neural_coder/backends/onnx_inc_static_quant_qlinear.yaml
neural_coder/backends/pytorch_aliblade.yaml
neural_coder/backends/pytorch_benchmark.yaml
neural_coder/backends/pytorch_channels_last.yaml
neural_coder/backends/pytorch_inc_bf16.yaml
neural_coder/backends/pytorch_inc_dynamic_quant.yaml
neural_coder/backends/pytorch_inc_dynamic_quant_fp8.yaml
neural_coder/backends/pytorch_inc_huggingface_optimum_dynamic.yaml
neural_coder/backends/pytorch_inc_huggingface_optimum_static.yaml
neural_coder/backends/pytorch_inc_static_quant_fx.yaml
neural_coder/backends/pytorch_inc_static_quant_fx_fp8.yaml
neural_compressor_full-2.1.1.dist-info/LICENSE
neural_compressor_full-2.1.1.dist-info/METADATA
neural_compressor_full-2.1.1.dist-info/WHEEL
neural_compressor_full-2.1.1.dist-info/top_level.txt
neural_compressor_full-2.1.1.dist-info/RECORD
