Metadata-Version: 2.1
Name: neural-compressor-full
Version: 2.1.1
Summary: Repository of Intel® Neural Compressor
Home-page: https://github.com/intel/neural-compressor
Author: Intel AIA Team
Author-email: feng.tian@intel.com, haihao.shen@intel.com, suyue.chen@intel.com
License: Apache 2.0
Keywords: quantization,auto-tuning,post-training static quantization,post-training dynamic quantization,quantization-aware training,tuning strategy
Classifier: Intended Audience :: Science/Research
Classifier: Programming Language :: Python :: 3
Classifier: Topic :: Scientific/Engineering :: Artificial Intelligence
Classifier: License :: OSI Approved :: Apache Software License
Requires-Python: >=3.6.0
License-File: LICENSE
Requires-Dist: numpy
Requires-Dist: pyyaml
Requires-Dist: scikit-learn
Requires-Dist: schema
Requires-Dist: py-cpuinfo
Requires-Dist: pandas
Requires-Dist: pycocotools
Requires-Dist: opencv-python
Requires-Dist: requests
Requires-Dist: psutil
Requires-Dist: Pillow
Requires-Dist: prettytable
Requires-Dist: deprecated
Requires-Dist: Flask-Cors
Requires-Dist: Flask-SocketIO
Requires-Dist: Flask
Requires-Dist: gevent-websocket
Requires-Dist: gevent
Requires-Dist: sqlalchemy (==1.4.27)
Requires-Dist: alembic (==1.7.7)
Requires-Dist: cryptography
